LICENSE
MANIFEST.in
README.md
setup.cfg
setup.py
admin_notification/__init__.py
admin_notification/admin.py
admin_notification/apps.py
admin_notification/cache.py
admin_notification/compat.py
admin_notification/models.py
admin_notification/signals.py
admin_notification/tests.py
admin_notification/version.py
admin_notification/views.py
admin_notification/migrations/0001_initial.py
admin_notification/migrations/0002_notification_active.py
admin_notification/migrations/0003_alter_notification_count.py
admin_notification/migrations/__init__.py
admin_notification/static/admin_notification/css/notifications.css
admin_notification/static/admin_notification/img/notification.png
admin_notification/templates/admin/base_site.html
admin_notification/templatetags/__init__.py
admin_notification/templatetags/admin_notification_tags.py
django_admin_notification.egg-info/PKG-INFO
django_admin_notification.egg-info/SOURCES.txt
django_admin_notification.egg-info/dependency_links.txt
django_admin_notification.egg-info/requires.txt
django_admin_notification.egg-info/top_level.txt